datapilot/__init__.py
datapilot/checker.py
data_pilot_checker-1.6.dist-info/LICENSE
data_pilot_checker-1.6.dist-info/METADATA
data_pilot_checker-1.6.dist-info/WHEEL
data_pilot_checker-1.6.dist-info/top_level.txt
data_pilot_checker-1.6.dist-info/RECORD
