Metadata-Version: 2.1
Name: data_pilot_checker
Version: 1.6
Summary: A package for automating data quality and integrity checks with optional GPU acceleration using cuDF
Home-page: https://github.com/Sarvesh-GanesanW/datapilot
Author: Sarvesh Ganesan
Author-email: sarveshganesanwork@gmail.com
Classifier: Programming Language :: Python :: 3
Classifier: License :: OSI Approved :: MIT License
Classifier: Operating System :: OS Independent
Requires-Python: >=3.11
License-File: LICENSE
Requires-Dist: pandas
Requires-Dist: dask[dataframe]
Requires-Dist: matplotlib
Requires-Dist: aiohttp
Requires-Dist: openai
Requires-Dist: asyncio
Requires-Dist: colored
